LICENSE.txt
MANIFEST.in
README.rst
setup.py
docs/Makefile
docs/conf.py
docs/index.rst
fossilize/__init__.py
fossilize/api.py
fossilize/main.py
fossilize.egg-info/PKG-INFO
fossilize.egg-info/SOURCES.txt
fossilize.egg-info/dependency_links.txt
fossilize.egg-info/entry_points.txt
fossilize.egg-info/top_level.txt
tests/.coveragerc