Metadata-Version: 1.0
Name: fossilize
Version: 0.2.0
Summary: UNKNOWN
Home-page: UNKNOWN
Author: Kale Kundert
Author-email: kale@thekunderts.net
License: UNKNOWN
Platform: UNKNOWN
